env_paths/__init__.py
env_paths/backup.py
env_paths/main.py
env_paths-1.0.1.dist-info/WHEEL
env_paths-1.0.1.dist-info/METADATA
env_paths-1.0.1.dist-info/RECORD
