Metadata-Version: 2.1
Name: env-paths
Version: 1.0.1
Summary: Returns the directory where the cache is located. This is different for each os.
Home-page: https://github.com/atu4403
Author: atu4403
Author-email: 73111778+atu4403@users.noreply.github.com
Requires-Python: >=3.8,<4.0
Classifier: Programming Language :: Python :: 3
Classifier: Programming Language :: Python :: 3.8
Classifier: Programming Language :: Python :: 3.9
Project-URL: Repository, https://github.com/atu4403/env-paths
